llama_index/packs/llama_dataset_metadata/__init__.py
llama_index/packs/llama_dataset_metadata/base.py
llama_index_packs_llama_dataset_metadata-0.4.1.dist-info/METADATA
llama_index_packs_llama_dataset_metadata-0.4.1.dist-info/WHEEL
llama_index_packs_llama_dataset_metadata-0.4.1.dist-info/licenses/LICENSE
llama_index_packs_llama_dataset_metadata-0.4.1.dist-info/RECORD
