Metadata-Version: 2.4
Name: llama-index-packs-llama-dataset-metadata
Version: 0.4.1
Summary: llama-index packs llama_dataset_metadata integration
Author-email: Your Name <you@example.com>
Maintainer: nerdai
License-Expression: MIT
License-File: LICENSE
Keywords: evaluation,llamadataset,rag,submission
Requires-Python: <4.0,>=3.9
Requires-Dist: llama-index-core<0.15,>=0.13.0
Requires-Dist: pandas
